llmling_agent/__init__.py
llmling_agent/__main__.py
llmling_agent/base_provider.py
llmling_agent/common_types.py
llmling_agent/log.py
llmling_agent/py.typed
llmling_agent/resource_registry.py
llmling_agent/splitter.py
llmling_agent/storage.py
llmling_agent/agent/__init__.py
llmling_agent/agent/agent.py
llmling_agent/agent/architect.py
llmling_agent/agent/context.py
llmling_agent/agent/conversation.py
llmling_agent/agent/interactions.py
llmling_agent/agent/structured.py
llmling_agent/agent/sys_prompts.py
llmling_agent/config/__init__.py
llmling_agent/config/capabilities.py
llmling_agent/config_resources/__init__.py
llmling_agent/config_resources/agents.yml
llmling_agent/config_resources/agents_template.yml
llmling_agent/delegation/__init__.py
llmling_agent/delegation/base_team.py
llmling_agent/delegation/message_flow_tracker.py
llmling_agent/delegation/pool.py
llmling_agent/delegation/structured_team.py
llmling_agent/delegation/team.py
llmling_agent/delegation/teamrun.py
llmling_agent/mcp_server/__init__.py
llmling_agent/mcp_server/client.py
llmling_agent/mcp_server/manager.py
llmling_agent/mcp_server/registry.py
llmling_agent/messaging/__init__.py
llmling_agent/messaging/connection_manager.py
llmling_agent/messaging/context.py
llmling_agent/messaging/event_manager.py
llmling_agent/messaging/eventnode.py
llmling_agent/messaging/events.py
llmling_agent/messaging/message_container.py
llmling_agent/messaging/messageemitter.py
llmling_agent/messaging/messagenode.py
llmling_agent/messaging/messages.py
llmling_agent/messaging/node_logger.py
llmling_agent/models/__init__.py
llmling_agent/models/agents.py
llmling_agent/models/content.py
llmling_agent/models/manifest.py
llmling_agent/observability/__init__.py
llmling_agent/observability/decorators.py
llmling_agent/observability/observability_registry.py
llmling_agent/prompts/__init__.py
llmling_agent/prompts/base.py
llmling_agent/prompts/builtin_provider.py
llmling_agent/prompts/conversion_manager.py
mseep_llmling_agent-0.99.51.dist-info/METADATA
mseep_llmling_agent-0.99.51.dist-info/WHEEL
mseep_llmling_agent-0.99.51.dist-info/entry_points.txt
mseep_llmling_agent-0.99.51.dist-info/licenses/LICENSE
mseep_llmling_agent-0.99.51.dist-info/RECORD
